sdamgia/__init__.py
sdamgia/api.py
sdamgia/enums.py
sdamgia/py.typed
sdamgia/types.py
sdamgia/utils.py
sdamgia-0.2.0.dist-info/LICENSE
sdamgia-0.2.0.dist-info/METADATA
sdamgia-0.2.0.dist-info/WHEEL
sdamgia-0.2.0.dist-info/RECORD
