Metadata-Version: 2.1
Name: sdamgia
Version: 0.2.0
Summary: Unofficial API for SdamGIA educational portal for exam preparation written in Python.
License: LGPL-3.0-or-later
Keywords: sdamgia,api,asyncio
Author: Динаzavr
Author-email: dinaprk@cumallover.me
Requires-Python: >=3.10,<4.0
Classifier: Development Status :: 4 - Beta
Classifier: Environment :: Console
Classifier: Framework :: AsyncIO
Classifier: Intended Audience :: Developers
Classifier: License :: OSI Approved :: GNU Lesser General Public License v3 or later (LGPLv3+)
Classifier: Operating System :: OS Independent
Classifier: Programming Language :: Python :: 3
Classifier: Programming Language :: Python :: 3.10
Classifier: Programming Language :: Python :: 3.11
Classifier: Programming Language :: Python :: 3.12
Classifier: Programming Language :: Python :: 3 :: Only
Classifier: Topic :: Software Development :: Libraries :: Python Modules
Classifier: Typing :: Typed
Provides-Extra: pix2tex
Requires-Dist: aiohttp (>=3.9.5,<4.0.0)
Requires-Dist: cairosvg (>=2.7.0,<3.0.0)
Requires-Dist: pillow (>=10.2.0,<11.0.0)
Requires-Dist: pix2tex[cli] (>=0.1.2,<0.2.0) ; extra == "pix2tex"
Requires-Dist: selectolax (>=0.3.21,<0.4.0)
Project-URL: Documentation, https://dinaprk.github.io/sdamgia-python
Project-URL: Issue Tracker, https://github.com/dinaprk/sdamgia-python/issues
Project-URL: Repository, https://github.com/dinaprk/sdamgia-python
